shellfoundry_traffic/__init__.py
shellfoundry_traffic/__main__.py
shellfoundry_traffic/cloudshell_scripts_helpers.py
shellfoundry_traffic/script_utils.py
shellfoundry_traffic/shellfoundry_traffic_cmd.py
shellfoundry_traffic/test_helpers.py
shellfoundry_traffic-0.3.0.dist-info/METADATA
shellfoundry_traffic-0.3.0.dist-info/WHEEL
shellfoundry_traffic-0.3.0.dist-info/entry_points.txt
shellfoundry_traffic-0.3.0.dist-info/top_level.txt
shellfoundry_traffic-0.3.0.dist-info/RECORD
