Metadata-Version: 2.1
Name: shellfoundry-traffic
Version: 0.3.0
Summary: Extension to Quali shellfoundry package for TG shells development
Home-page: https://github.com/QualiSystems/shellfoundry-traffic
Author: Quali
Author-email: info@qualisystems.com
License: Apache Software License
Classifier: Development Status :: 5 - Production/Stable
Classifier: Natural Language :: English
Classifier: License :: OSI Approved :: Apache Software License
Classifier: Intended Audience :: Developers
Classifier: Operating System :: OS Independent
Classifier: Topic :: Software Development :: Testing
Classifier: Programming Language :: Python :: 3.9
Requires-Dist: PyYAML
Requires-Dist: pytest
Requires-Dist: cloudshell-logging (==1.0.3)
Requires-Dist: cloudshell-orch-core (<3.4.0.0,>=3.3.0.0)
Requires-Dist: cloudshell-shell-core (<6.0.0,>=5.0.3)
Requires-Dist: cloudshell-rest-api (>=8.2.3.1)
Requires-Dist: shellfoundry
